ocgraph/__init__.py
ocgraph/__main__.py
ocgraph/configuration/__init__.py
ocgraph/configuration/architecture/__init__.py
ocgraph/configuration/architecture/architecture.py
ocgraph/configuration/architecture/arm.py
ocgraph/configuration/architecture/msp430.py
ocgraph/configuration/architecture/ppc.py
ocgraph/configuration/architecture/sparc.py
ocgraph/configuration/architecture/x86.py
ocgraph/configuration/configuration.py
ocgraph/configuration/disassembler/__init__.py
ocgraph/configuration/disassembler/disassembler.py
ocgraph/configuration/disassembler/gdb_default.py
ocgraph/configuration/disassembler/objdump_arm.py
ocgraph/configuration/disassembler/objdump_msp430.py
ocgraph/configuration/disassembler/objdump_ppc.py
ocgraph/configuration/disassembler/objdump_sparc.py
ocgraph/configuration/disassembler/objdump_x86.py
ocgraph/configuration/logger.py
ocgraph/data/__init__.py
ocgraph/data/address.py
ocgraph/data/basic_block.py
ocgraph/data/encoding.py
ocgraph/data/function_header.py
ocgraph/data/instruction.py
ocgraph/data/jump_table.py
ocgraph/interface/__init__.py
ocgraph/interface/analyzer.py
ocgraph/interface/coverage_reader.py
ocgraph/interface/drawer.py
ocgraph-0.3.0.dist-info/LICENSES/GTDGmbH.md
ocgraph-0.3.0.dist-info/LICENSES/MauriMustonen.md
ocgraph-0.3.0.dist-info/METADATA
ocgraph-0.3.0.dist-info/WHEEL
ocgraph-0.3.0.dist-info/entry_points.txt
ocgraph-0.3.0.dist-info/RECORD
