Metadata-Version: 2.3
Name: ocgraph
Version: 0.3.0
Summary: Tool to visualize object code as control flow graph
License: MIT
Keywords: Object Code,Control Flow Graph,ECSS Category A,asm2cfg,Coverage
Author: Mauri Mustonen
Author-email: kazooiebombchu@gmail.com
Maintainer: Christoph Weiss
Maintainer-email: christoph.weiss@gtd-gmbh.de
Requires-Python: >=3.9,<4.0
Classifier: Development Status :: 4 - Beta
Classifier: License :: OSI Approved :: MIT License
Classifier: Programming Language :: Python :: 3
Classifier: Programming Language :: Python :: 3.9
Classifier: Programming Language :: Python :: 3.10
Classifier: Programming Language :: Python :: 3.11
Classifier: Programming Language :: Python :: 3.12
Classifier: Programming Language :: Python :: 3.13
Requires-Dist: graphviz (>=0.9,<0.10)
Project-URL: Documentation, https://gtd-gmbh.gitlab.io/beta-software/ocgraph
Project-URL: Forked from asm2cfg, https://github.com/Kazhuu/asm2cfg
Project-URL: Homepage, https://gtd-gmbh.de/cat-a
Project-URL: Repository, https://gitlab.com/gtd-gmbh/beta-software/ocgraph.git
